setup.py
RegistroBR/__init__.py
RegistroBR/avail_client.py
RegistroBR.egg-info/PKG-INFO
RegistroBR.egg-info/SOURCES.txt
RegistroBR.egg-info/dependency_links.txt
RegistroBR.egg-info/top_level.txt