Metadata-Version: 1.1
Name: RegistroBR
Version: 0.5
Summary: A custom library for contacting the RegistroBR API
Home-page: https://github.com/zoidbergwill/RegistroBR
Author: Code originally by RegistroBR. Modified by William Stewart
Author-email: zoidbergwill@gmail.com
License: Custom Registro.br License
Keywords: registro.br .com.br domains
Platform: UNKNOWN
Classifier: Development Status :: 5 - Production/Stable
Classifier: Environment :: Console
Classifier: Intended Audience :: Customer Service
Classifier: Intended Audience :: Developers
Classifier: Intended Audience :: End Users/Desktop
Classifier: Intended Audience :: Information Technology
Classifier: License :: OSI Approved :: MIT License
Classifier: Natural Language :: English
Classifier: Programming Language :: Python :: 2.4
Classifier: Programming Language :: Python :: 2.5
Classifier: Programming Language :: Python :: 2.6
Classifier: Programming Language :: Python :: 2.7
